{
	"configurations" : 
	[
		{
			"directories" : 
			[
				{
					"build" : ".",
					"minimumCMakeVersion" : 
					{
						"string" : "3.0"
					},
					"projectIndex" : 0,
					"source" : ".",
					"targetIndexes" : 
					[
						0
					]
				}
			],
			"name" : "Debug",
			"projects" : 
			[
				{
					"directoryIndexes" : 
					[
						0
					],
					"name" : "SOLIDERFIRE",
					"targetIndexes" : 
					[
						0
					]
				}
			],
			"targets" : 
			[
				{
					"directoryIndex" : 0,
					"id" : "my_cmake_exe::@6890427a1f51a3e7e1df",
					"jsonFile" : "target-my_cmake_exe-Debug-49bd457411ba11c7e47b.json",
					"name" : "my_cmake_exe",
					"projectIndex" : 0
				}
			]
		}
	],
	"kind" : "codemodel",
	"paths" : 
	{
		"build" : "/home/acs/project/Soloder_Gun/build",
		"source" : "/home/acs/project/Soloder_Gun"
	},
	"version" : 
	{
		"major" : 2,
		"minor" : 0
	}
}
